{
    "version": 1,
    "screenName": "SettingsMenu",
    "themePath": "Assets/ui/BicycleSim_DarkTheme.ui.theme.json",
    "screenSettings": {
        "visible": false,
        "blocksInput": true,
        "renderOrder": 3,
        "pauseGameWhenOpen": true,
        "allowInputPassthrough": false,
        "enterAnimation": "SettingsMenu_FadeIn",
        "exitAnimation": "SettingsMenu_FadeOut",
        "hideAfterExit": true,
        "blockInputDuringTransition": true
    },
    "canvasReferenceResolution": {
        "x": 1920.0,
        "y": 1080.0
    },
    "bindings": [
        {
            "targetElementId": 6,
            "targetProperty": "Slider.value",
            "sourceKey": "ui.globalScale",
            "formatString": "",
            "invert": false,
            "updateMode": "OnChange",
            "min": 0.5,
            "max": 2.5
        },
        {
            "targetElementId": 8,
            "targetProperty": "Slider.value",
            "sourceKey": "ui.hudOpacity",
            "formatString": "",
            "invert": false,
            "updateMode": "OnChange",
            "min": 0.0,
            "max": 1.0
        }
    ],
    "animations": [
        {
            "name": "SettingsMenu_FadeIn",
            "duration": 0.25,
            "loopCount": 1,
            "playOnShow": true,
            "trackCount": 1,
            "tracks": [
                {
                    "targetElementId": 2,
                    "property": "Opacity",
                    "keyframes": [
                        { "time": 0.0, "value": { "type": "Float", "value": 0.0 }, "easing": "EaseOut" },
                        { "time": 0.25, "value": { "type": "Float", "value": 1.0 }, "easing": "EaseOut" }
                    ]
                }
            ]
        },
        {
            "name": "SettingsMenu_FadeOut",
            "duration": 0.20,
            "loopCount": 1,
            "playOnShow": false,
            "trackCount": 1,
            "tracks": [
                {
                    "targetElementId": 2,
                    "property": "Opacity",
                    "keyframes": [
                        { "time": 0.0, "value": { "type": "Float", "value": 1.0 }, "easing": "EaseIn" },
                        { "time": 0.20, "value": { "type": "Float", "value": 0.0 }, "easing": "EaseIn" }
                    ]
                }
            ]
        }
    ],
    "rootElement": {
        "id": 1,
        "name": "Canvas",
        "type": "Canvas",
        "visible": true,
        "enabled": true,
        "interactable": false,
        "zOrder": 0,
        "transform": {
            "position": { "x": 0.0, "y": 0.0 },
            "size": { "x": 1920.0, "y": 1080.0 },
            "anchorMin": { "x": 0.0, "y": 0.0 },
            "anchorMax": { "x": 0.0, "y": 0.0 },
            "pivot": { "x": 0.0, "y": 0.0 },
            "rotation": 0.0,
            "scale": { "x": 1.0, "y": 1.0 }
        },
        "style": {
            "backgroundColor": { "x": 0.0, "y": 0.0, "z": 0.0, "w": 0.0 },
            "tintColor": { "x": 1.0, "y": 1.0, "z": 1.0, "w": 1.0 },
            "textColor": { "x": 1.0, "y": 1.0, "z": 1.0, "w": 1.0 },
            "texturePath": "",
            "fontPath": "Assets/Fonts/simhei.ttf",
            "fontSize": 16.0,
            "opacity": 1.0,
            "padding": { "left": 0.0, "top": 0.0, "right": 0.0, "bottom": 0.0 },
            "margin": { "left": 0.0, "top": 0.0, "right": 0.0, "bottom": 0.0 },
            "borderColor": { "x": 0.0, "y": 0.0, "z": 0.0, "w": 0.0 },
            "borderWidth": 0.0,
            "borderRadius": 0.0
        },
        "widgetData": {},
        "events": { "onClick": "", "onHover": "", "onPressed": "", "onReleased": "", "onValueChanged": "" },
        "children": [
            {
                "id": 2,
                "name": "SettingsOverlay",
                "type": "Panel",
                "visible": true,
                "enabled": true,
                "interactable": false,
                "zOrder": 0,
                "transform": {
                    "position": { "x": 0.0, "y": 0.0 },
                    "size": { "x": 1920.0, "y": 1080.0 },
                    "anchorMin": { "x": 0.0, "y": 0.0 },
                    "anchorMax": { "x": 0.0, "y": 0.0 },
                    "pivot": { "x": 0.0, "y": 0.0 },
                    "rotation": 0.0,
                    "scale": { "x": 1.0, "y": 1.0 }
                },
                "style": {
                    "presetName": "TransparentPanel",
                    "overrides": { "backgroundColor": true },
                    "backgroundColor": { "x": 0.02, "y": 0.04, "z": 0.08, "w": 0.86 },
                    "tintColor": { "x": 1.0, "y": 1.0, "z": 1.0, "w": 1.0 },
                    "textColor": { "x": 1.0, "y": 1.0, "z": 1.0, "w": 1.0 },
                    "texturePath": "",
                    "fontPath": "",
                    "fontSize": 16.0,
                    "opacity": 1.0,
                    "padding": { "left": 0.0, "top": 0.0, "right": 0.0, "bottom": 0.0 },
                    "margin": { "left": 0.0, "top": 0.0, "right": 0.0, "bottom": 0.0 },
                    "borderColor": { "x": 0.0, "y": 0.0, "z": 0.0, "w": 0.0 },
                    "borderWidth": 0.0,
                    "borderRadius": 0.0
                },
                "widgetData": {},
                "events": { "onClick": "", "onHover": "", "onPressed": "", "onReleased": "", "onValueChanged": "" },
                "children": []
            },
            {
                "id": 3,
                "name": "SettingsTitle",
                "type": "Text",
                "visible": true,
                "enabled": true,
                "interactable": false,
                "zOrder": 1,
                "transform": {
                    "position": { "x": 960.0, "y": 160.0 },
                    "size": { "x": 540.0, "y": 80.0 },
                    "anchorMin": { "x": 0.0, "y": 0.0 },
                    "anchorMax": { "x": 0.0, "y": 0.0 },
                    "pivot": { "x": 0.5, "y": 0.5 },
                    "rotation": 0.0,
                    "scale": { "x": 1.0, "y": 1.0 }
                },
                "style": {
                    "presetName": "",
                    "overrides": {},
                    "backgroundColor": { "x": 0.0, "y": 0.0, "z": 0.0, "w": 0.0 },
                    "tintColor": { "x": 1.0, "y": 1.0, "z": 1.0, "w": 1.0 },
                    "textColor": { "x": 1.0, "y": 1.0, "z": 1.0, "w": 1.0 },
                    "texturePath": "",
                    "fontPath": "Assets/Fonts/Dengb.ttf",
                    "fontSize": 42.0,
                    "opacity": 1.0,
                    "padding": { "left": 0.0, "top": 0.0, "right": 0.0, "bottom": 0.0 },
                    "margin": { "left": 0.0, "top": 0.0, "right": 0.0, "bottom": 0.0 },
                    "borderColor": { "x": 0.0, "y": 0.0, "z": 0.0, "w": 0.0 },
                    "borderWidth": 0.0,
                    "borderRadius": 0.0
                },
                "widgetData": {
                    "text": "Settings",
                    "alignment": "Center",
                    "wrapText": false
                },
                "events": { "onClick": "", "onHover": "", "onPressed": "", "onReleased": "", "onValueChanged": "" },
                "children": []
            },
            {
                "id": 4,
                "name": "MasterVolumeLabel",
                "type": "Text",
                "visible": true,
                "enabled": true,
                "interactable": false,
                "zOrder": 1,
                "transform": {
                    "position": { "x": 620.0, "y": 300.0 },
                    "size": { "x": 300.0, "y": 40.0 },
                    "anchorMin": { "x": 0.0, "y": 0.0 },
                    "anchorMax": { "x": 0.0, "y": 0.0 },
                    "pivot": { "x": 0.0, "y": 0.0 },
                    "rotation": 0.0,
                    "scale": { "x": 1.0, "y": 1.0 }
                },
                "style": {
                    "presetName": "HudText",
                    "overrides": { "fontSize": true },
                    "backgroundColor": { "x": 0.0, "y": 0.0, "z": 0.0, "w": 0.0 },
                    "tintColor": { "x": 1.0, "y": 1.0, "z": 1.0, "w": 1.0 },
                    "textColor": { "x": 0.90, "y": 0.92, "z": 0.96, "w": 1.0 },
                    "texturePath": "",
                    "fontPath": "Assets/Fonts/simhei.ttf",
                    "fontSize": 24.0,
                    "opacity": 1.0,
                    "padding": { "left": 0.0, "top": 0.0, "right": 0.0, "bottom": 0.0 },
                    "margin": { "left": 0.0, "top": 0.0, "right": 0.0, "bottom": 0.0 },
                    "borderColor": { "x": 0.0, "y": 0.0, "z": 0.0, "w": 0.0 },
                    "borderWidth": 0.0,
                    "borderRadius": 0.0
                },
                "widgetData": {
                    "text": "Master Volume",
                    "alignment": "Left",
                    "wrapText": false
                },
                "events": { "onClick": "", "onHover": "", "onPressed": "", "onReleased": "", "onValueChanged": "" },
                "children": []
            },
            {
                "id": 5,
                "name": "MasterVolumeSlider",
                "type": "Slider",
                "visible": true,
                "enabled": true,
                "interactable": true,
                "zOrder": 2,
                "transform": {
                    "position": { "x": 620.0, "y": 348.0 },
                    "size": { "x": 680.0, "y": 36.0 },
                    "anchorMin": { "x": 0.0, "y": 0.0 },
                    "anchorMax": { "x": 0.0, "y": 0.0 },
                    "pivot": { "x": 0.0, "y": 0.0 },
                    "rotation": 0.0,
                    "scale": { "x": 1.0, "y": 1.0 }
                },
                "style": {
                    "presetName": "",
                    "overrides": {},
                    "backgroundColor": { "x": 0.14, "y": 0.18, "z": 0.26, "w": 1.0 },
                    "tintColor": { "x": 1.0, "y": 1.0, "z": 1.0, "w": 1.0 },
                    "textColor": { "x": 0.95, "y": 0.95, "z": 0.98, "w": 1.0 },
                    "texturePath": "",
                    "fontPath": "",
                    "fontSize": 16.0,
                    "opacity": 1.0,
                    "padding": { "left": 0.0, "top": 0.0, "right": 0.0, "bottom": 0.0 },
                    "margin": { "left": 0.0, "top": 0.0, "right": 0.0, "bottom": 0.0 },
                    "borderColor": { "x": 0.40, "y": 0.46, "z": 0.62, "w": 1.0 },
                    "borderWidth": 1.0,
                    "borderRadius": 8.0
                },
                "widgetData": {
                    "minValue": 0.0,
                    "maxValue": 1.0,
                    "value": 0.75,
                    "wholeNumbers": false,
                    "fillColor": { "x": 0.35, "y": 0.72, "z": 0.96, "w": 1.0 },
                    "handleColor": { "x": 0.95, "y": 0.97, "z": 1.0, "w": 1.0 }
                },
                "events": { "onClick": "", "onHover": "", "onPressed": "", "onReleased": "", "onValueChanged": "" },
                "children": []
            },
            {
                "id": 40,
                "name": "UIScaleLabel",
                "type": "Text",
                "visible": true,
                "enabled": true,
                "interactable": false,
                "zOrder": 1,
                "transform": {
                    "position": { "x": 620.0, "y": 420.0 },
                    "size": { "x": 300.0, "y": 40.0 },
                    "anchorMin": { "x": 0.0, "y": 0.0 },
                    "anchorMax": { "x": 0.0, "y": 0.0 },
                    "pivot": { "x": 0.0, "y": 0.0 },
                    "rotation": 0.0,
                    "scale": { "x": 1.0, "y": 1.0 }
                },
                "style": {
                    "presetName": "HudText",
                    "overrides": { "fontSize": true },
                    "backgroundColor": { "x": 0.0, "y": 0.0, "z": 0.0, "w": 0.0 },
                    "tintColor": { "x": 1.0, "y": 1.0, "z": 1.0, "w": 1.0 },
                    "textColor": { "x": 0.90, "y": 0.92, "z": 0.96, "w": 1.0 },
                    "texturePath": "",
                    "fontPath": "Assets/Fonts/simhei.ttf",
                    "fontSize": 24.0,
                    "opacity": 1.0,
                    "padding": { "left": 0.0, "top": 0.0, "right": 0.0, "bottom": 0.0 },
                    "margin": { "left": 0.0, "top": 0.0, "right": 0.0, "bottom": 0.0 },
                    "borderColor": { "x": 0.0, "y": 0.0, "z": 0.0, "w": 0.0 },
                    "borderWidth": 0.0,
                    "borderRadius": 0.0
                },
                "widgetData": {
                    "text": "UI Scale",
                    "alignment": "Left",
                    "wrapText": false
                },
                "events": { "onClick": "", "onHover": "", "onPressed": "", "onReleased": "", "onValueChanged": "" },
                "children": []
            },
            {
                "id": 6,
                "name": "UIScaleSlider",
                "type": "Slider",
                "visible": true,
                "enabled": true,
                "interactable": true,
                "zOrder": 2,
                "transform": {
                    "position": { "x": 620.0, "y": 468.0 },
                    "size": { "x": 680.0, "y": 36.0 },
                    "anchorMin": { "x": 0.0, "y": 0.0 },
                    "anchorMax": { "x": 0.0, "y": 0.0 },
                    "pivot": { "x": 0.0, "y": 0.0 },
                    "rotation": 0.0,
                    "scale": { "x": 1.0, "y": 1.0 }
                },
                "style": {
                    "presetName": "",
                    "overrides": {},
                    "backgroundColor": { "x": 0.14, "y": 0.18, "z": 0.26, "w": 1.0 },
                    "tintColor": { "x": 1.0, "y": 1.0, "z": 1.0, "w": 1.0 },
                    "textColor": { "x": 0.95, "y": 0.95, "z": 0.98, "w": 1.0 },
                    "texturePath": "",
                    "fontPath": "",
                    "fontSize": 16.0,
                    "opacity": 1.0,
                    "padding": { "left": 0.0, "top": 0.0, "right": 0.0, "bottom": 0.0 },
                    "margin": { "left": 0.0, "top": 0.0, "right": 0.0, "bottom": 0.0 },
                    "borderColor": { "x": 0.40, "y": 0.46, "z": 0.62, "w": 1.0 },
                    "borderWidth": 1.0,
                    "borderRadius": 8.0
                },
                "widgetData": {
                    "minValue": 0.5,
                    "maxValue": 2.5,
                    "value": 1.0,
                    "wholeNumbers": false,
                    "fillColor": { "x": 0.28, "y": 0.72, "z": 0.42, "w": 1.0 },
                    "handleColor": { "x": 0.95, "y": 0.97, "z": 1.0, "w": 1.0 }
                },
                "events": { "onClick": "", "onHover": "", "onPressed": "", "onReleased": "", "onValueChanged": "ui.globalScale" },
                "children": []
            },
            {
                "id": 41,
                "name": "HudOpacityLabel",
                "type": "Text",
                "visible": true,
                "enabled": true,
                "interactable": false,
                "zOrder": 1,
                "transform": {
                    "position": { "x": 620.0, "y": 540.0 },
                    "size": { "x": 300.0, "y": 40.0 },
                    "anchorMin": { "x": 0.0, "y": 0.0 },
                    "anchorMax": { "x": 0.0, "y": 0.0 },
                    "pivot": { "x": 0.0, "y": 0.0 },
                    "rotation": 0.0,
                    "scale": { "x": 1.0, "y": 1.0 }
                },
                "style": {
                    "presetName": "HudText",
                    "overrides": { "fontSize": true },
                    "backgroundColor": { "x": 0.0, "y": 0.0, "z": 0.0, "w": 0.0 },
                    "tintColor": { "x": 1.0, "y": 1.0, "z": 1.0, "w": 1.0 },
                    "textColor": { "x": 0.90, "y": 0.92, "z": 0.96, "w": 1.0 },
                    "texturePath": "",
                    "fontPath": "Assets/Fonts/simhei.ttf",
                    "fontSize": 24.0,
                    "opacity": 1.0,
                    "padding": { "left": 0.0, "top": 0.0, "right": 0.0, "bottom": 0.0 },
                    "margin": { "left": 0.0, "top": 0.0, "right": 0.0, "bottom": 0.0 },
                    "borderColor": { "x": 0.0, "y": 0.0, "z": 0.0, "w": 0.0 },
                    "borderWidth": 0.0,
                    "borderRadius": 0.0
                },
                "widgetData": {
                    "text": "HUD Opacity",
                    "alignment": "Left",
                    "wrapText": false
                },
                "events": { "onClick": "", "onHover": "", "onPressed": "", "onReleased": "", "onValueChanged": "" },
                "children": []
            },
            {
                "id": 8,
                "name": "HudOpacitySlider",
                "type": "Slider",
                "visible": true,
                "enabled": true,
                "interactable": true,
                "zOrder": 2,
                "transform": {
                    "position": { "x": 620.0, "y": 588.0 },
                    "size": { "x": 680.0, "y": 36.0 },
                    "anchorMin": { "x": 0.0, "y": 0.0 },
                    "anchorMax": { "x": 0.0, "y": 0.0 },
                    "pivot": { "x": 0.0, "y": 0.0 },
                    "rotation": 0.0,
                    "scale": { "x": 1.0, "y": 1.0 }
                },
                "style": {
                    "presetName": "",
                    "overrides": {},
                    "backgroundColor": { "x": 0.14, "y": 0.18, "z": 0.26, "w": 1.0 },
                    "tintColor": { "x": 1.0, "y": 1.0, "z": 1.0, "w": 1.0 },
                    "textColor": { "x": 0.95, "y": 0.95, "z": 0.98, "w": 1.0 },
                    "texturePath": "",
                    "fontPath": "",
                    "fontSize": 16.0,
                    "opacity": 1.0,
                    "padding": { "left": 0.0, "top": 0.0, "right": 0.0, "bottom": 0.0 },
                    "margin": { "left": 0.0, "top": 0.0, "right": 0.0, "bottom": 0.0 },
                    "borderColor": { "x": 0.40, "y": 0.46, "z": 0.62, "w": 1.0 },
                    "borderWidth": 1.0,
                    "borderRadius": 8.0
                },
                "widgetData": {
                    "minValue": 0.0,
                    "maxValue": 1.0,
                    "value": 1.0,
                    "wholeNumbers": false,
                    "fillColor": { "x": 0.86, "y": 0.67, "z": 0.26, "w": 1.0 },
                    "handleColor": { "x": 0.95, "y": 0.97, "z": 1.0, "w": 1.0 }
                },
                "events": { "onClick": "", "onHover": "", "onPressed": "", "onReleased": "", "onValueChanged": "ui.hudOpacity" },
                "children": []
            },
            {
                "id": 42,
                "name": "ShowDebugHudLabel",
                "type": "Text",
                "visible": true,
                "enabled": true,
                "interactable": false,
                "zOrder": 1,
                "transform": {
                    "position": { "x": 620.0, "y": 660.0 },
                    "size": { "x": 300.0, "y": 40.0 },
                    "anchorMin": { "x": 0.0, "y": 0.0 },
                    "anchorMax": { "x": 0.0, "y": 0.0 },
                    "pivot": { "x": 0.0, "y": 0.0 },
                    "rotation": 0.0,
                    "scale": { "x": 1.0, "y": 1.0 }
                },
                "style": {
                    "presetName": "HudText",
                    "overrides": { "fontSize": true },
                    "backgroundColor": { "x": 0.0, "y": 0.0, "z": 0.0, "w": 0.0 },
                    "tintColor": { "x": 1.0, "y": 1.0, "z": 1.0, "w": 1.0 },
                    "textColor": { "x": 0.90, "y": 0.92, "z": 0.96, "w": 1.0 },
                    "texturePath": "",
                    "fontPath": "Assets/Fonts/simhei.ttf",
                    "fontSize": 24.0,
                    "opacity": 1.0,
                    "padding": { "left": 0.0, "top": 0.0, "right": 0.0, "bottom": 0.0 },
                    "margin": { "left": 0.0, "top": 0.0, "right": 0.0, "bottom": 0.0 },
                    "borderColor": { "x": 0.0, "y": 0.0, "z": 0.0, "w": 0.0 },
                    "borderWidth": 0.0,
                    "borderRadius": 0.0
                },
                "widgetData": {
                    "text": "Show Debug HUD",
                    "alignment": "Left",
                    "wrapText": false
                },
                "events": { "onClick": "", "onHover": "", "onPressed": "", "onReleased": "", "onValueChanged": "" },
                "children": []
            },
            {
                "id": 9,
                "name": "ShowDebugHudToggle",
                "type": "Toggle",
                "visible": true,
                "enabled": true,
                "interactable": true,
                "zOrder": 2,
                "transform": {
                    "position": { "x": 960.0, "y": 660.0 },
                    "size": { "x": 140.0, "y": 40.0 },
                    "anchorMin": { "x": 0.0, "y": 0.0 },
                    "anchorMax": { "x": 0.0, "y": 0.0 },
                    "pivot": { "x": 0.0, "y": 0.0 },
                    "rotation": 0.0,
                    "scale": { "x": 1.0, "y": 1.0 }
                },
                "style": {
                    "presetName": "",
                    "overrides": {},
                    "backgroundColor": { "x": 0.14, "y": 0.18, "z": 0.26, "w": 1.0 },
                    "tintColor": { "x": 1.0, "y": 1.0, "z": 1.0, "w": 1.0 },
                    "textColor": { "x": 0.95, "y": 0.95, "z": 0.98, "w": 1.0 },
                    "texturePath": "",
                    "fontPath": "",
                    "fontSize": 16.0,
                    "opacity": 1.0,
                    "padding": { "left": 0.0, "top": 0.0, "right": 0.0, "bottom": 0.0 },
                    "margin": { "left": 0.0, "top": 0.0, "right": 0.0, "bottom": 0.0 },
                    "borderColor": { "x": 0.40, "y": 0.46, "z": 0.62, "w": 1.0 },
                    "borderWidth": 1.0,
                    "borderRadius": 8.0
                },
                "widgetData": {
                    "label": "",
                    "isOn": false,
                    "onColor": { "x": 0.28, "y": 0.72, "z": 0.42, "w": 1.0 },
                    "offColor": { "x": 0.32, "y": 0.34, "z": 0.40, "w": 1.0 },
                    "knobColor": { "x": 0.95, "y": 0.97, "z": 1.0, "w": 1.0 }
                },
                "events": { "onClick": "", "onHover": "", "onPressed": "", "onReleased": "", "onValueChanged": "ui.showDebugHud" },
                "children": []
            },
            {
                "id": 10,
                "name": "BackButton",
                "type": "Button",
                "visible": true,
                "enabled": true,
                "interactable": true,
                "zOrder": 3,
                "transform": {
                    "position": { "x": 760.0, "y": 780.0 },
                    "size": { "x": 400.0, "y": 70.0 },
                    "anchorMin": { "x": 0.0, "y": 0.0 },
                    "anchorMax": { "x": 0.0, "y": 0.0 },
                    "pivot": { "x": 0.0, "y": 0.0 },
                    "rotation": 0.0,
                    "scale": { "x": 1.0, "y": 1.0 }
                },
                "style": {
                    "presetName": "PrimaryButton",
                    "overrides": {},
                    "backgroundColor": { "x": 0.18, "y": 0.22, "z": 0.32, "w": 0.98 },
                    "tintColor": { "x": 1.0, "y": 1.0, "z": 1.0, "w": 1.0 },
                    "textColor": { "x": 1.0, "y": 1.0, "z": 1.0, "w": 1.0 },
                    "texturePath": "",
                    "fontPath": "Assets/Fonts/simhei.ttf",
                    "fontSize": 28.0,
                    "opacity": 1.0,
                    "padding": { "left": 0.0, "top": 0.0, "right": 0.0, "bottom": 0.0 },
                    "margin": { "left": 0.0, "top": 0.0, "right": 0.0, "bottom": 0.0 },
                    "borderColor": { "x": 0.66, "y": 0.76, "z": 0.98, "w": 0.95 },
                    "borderWidth": 2.0,
                    "borderRadius": 14.0
                },
                "widgetData": {
                    "label": "Back",
                    "pressed": false,
                    "usePresetTransitionStyle": true,
                    "normalColor": { "x": 0.18, "y": 0.22, "z": 0.32, "w": 0.98 },
                    "hoverColor": { "x": 0.28, "y": 0.34, "z": 0.48, "w": 1.0 },
                    "pressedColor": { "x": 0.13, "y": 0.16, "z": 0.24, "w": 1.0 },
                    "disabledColor": { "x": 0.24, "y": 0.24, "z": 0.28, "w": 0.80 }
                },
                "events": { "onClick": "CloseSettings", "onHover": "", "onPressed": "", "onReleased": "", "onValueChanged": "" },
                "children": []
            }
        ]
    }
}
